aequitas/__init__.py
aequitas/audit.py
aequitas/bias.py
aequitas/fairness.py
aequitas/group.py
aequitas/plotting.py
aequitas/preprocessing.py
aequitas/squarify_flipped.py
aequitas/version.py
aequitas/flow/__init__.py
aequitas/flow/datasets/__init__.py
aequitas/flow/datasets/baf.py
aequitas/flow/datasets/dataset.py
aequitas/flow/datasets/folktables.py
aequitas/flow/datasets/generic.py
aequitas/flow/evaluation/__init__.py
aequitas/flow/evaluation/fairness.py
aequitas/flow/evaluation/performance.py
aequitas/flow/experiment/__init__.py
aequitas/flow/experiment/_configs.py
aequitas/flow/experiment/default.py
aequitas/flow/experiment/experiment.py
aequitas/flow/methods/__init__.py
aequitas/flow/methods/base_estimator/__init__.py
aequitas/flow/methods/base_estimator/base_estimator.py
aequitas/flow/methods/base_estimator/lightgbm.py
aequitas/flow/methods/base_estimator/logistic_regression.py
aequitas/flow/methods/base_estimator/neural_network.py
aequitas/flow/methods/base_estimator/random_forest.py
aequitas/flow/methods/inprocessing/__init__.py
aequitas/flow/methods/inprocessing/fairgbm.py
aequitas/flow/methods/inprocessing/fairlearn_classifier.py
aequitas/flow/methods/inprocessing/inprocessing.py
aequitas/flow/methods/postprocessing/__init__.py
aequitas/flow/methods/postprocessing/balanced_group_threshold.py
aequitas/flow/methods/postprocessing/group_threshold.py
aequitas/flow/methods/postprocessing/identity.py
aequitas/flow/methods/postprocessing/postprocessing.py
aequitas/flow/methods/postprocessing/threshold.py
aequitas/flow/methods/preprocessing/__init__.py
aequitas/flow/methods/preprocessing/data_repairer.py
aequitas/flow/methods/preprocessing/identity.py
aequitas/flow/methods/preprocessing/label_flipping.py
aequitas/flow/methods/preprocessing/preprocessing.py
aequitas/flow/methods/preprocessing/prevalence_sample.py
aequitas/flow/methods/preprocessing/unawareness.py
aequitas/flow/optimization/__init__.py
aequitas/flow/plots/__init__.py
aequitas-1.0.0.dist-info/AUTHORS.rst
aequitas-1.0.0.dist-info/LICENSE
aequitas-1.0.0.dist-info/METADATA
aequitas-1.0.0.dist-info/WHEEL
aequitas-1.0.0.dist-info/entry_points.txt
aequitas-1.0.0.dist-info/top_level.txt
aequitas-1.0.0.dist-info/RECORD
