Metadata-Version: 2.1
Name: aequitas
Version: 1.0.0
Summary: The bias and fairness audit toolkit.
Home-page: https://github.com/dssg/aequitas
Author: Center for Data Science and Public Policy
Author-email: datascifellows@gmail.com
License: MIT
Keywords: fairness bias aequitas
Classifier: Development Status :: 4 - Beta
Classifier: Intended Audience :: Developers
Classifier: License :: OSI Approved :: MIT License
Classifier: Natural Language :: English
Classifier: Programming Language :: Python :: 3
Classifier: Programming Language :: Python :: 3.7
Classifier: Programming Language :: Python :: 3.8
Classifier: Programming Language :: Python :: 3.9
Classifier: Programming Language :: Python :: 3.10
Classifier: Programming Language :: Python :: 3.11
Provides-Extra: webapp
Provides-Extra: cli
License-File: LICENSE
License-File: AUTHORS.rst
